{
  "configVersion": 1,
  "index": "/index.html",
  "assetGroups": [
    {
      "name": "app",
      "installMode": "prefetch",
      "updateMode": "prefetch",
      "urls": [
        "/favicon.png",
        "/index.html",
        "/main.b33a86962736ad465219.js",
        "/polyfills.25cec9eb998dda884ce9.js",
        "/runtime.7f706c09ba7459279236.js",
        "/styles.6830a36d5d686ed1fb76.js"
      ],
      "patterns": []
    },
    {
      "name": "assets",
      "installMode": "lazy",
      "updateMode": "prefetch",
      "urls": [
        "/assets/app-store-badge.png",
        "/assets/bg-colorful.png",
        "/assets/cipher.png",
        "/assets/donation-qr.svg",
        "/assets/google-play-badge.png",
        "/assets/metamask-network.png",
        "/assets/toshi.png",
        "/i18n/en.json",
        "/i18n/es.json"
      ],
      "patterns": []
    }
  ],
  "dataGroups": [],
  "hashTable": {
    "/assets/app-store-badge.png": "f573798aa1e1106c4ad3e3a593d7785287b375d1",
    "/assets/bg-colorful.png": "a76d79d85e272def58628f8bb6128a3129b2f158",
    "/assets/cipher.png": "9d68ca2d08a26dac20b5fd34d6a8394e65e8c0bb",
    "/assets/donation-qr.svg": "35ea2d45cfcd2db20ece8c219777d7496c95c78a",
    "/assets/google-play-badge.png": "dcb52ad53369d3388215d2a6d0c2895a733f7bf8",
    "/assets/metamask-network.png": "6f5bc166c9bb350cda57a9293213aa13f8c44394",
    "/assets/toshi.png": "bd849fac4d6f00b5cdfffd0f84053610cb868530",
    "/favicon.png": "75d5ba3d1973c0a65dd96d20456c23c110cee8d8",
    "/i18n/en.json": "26966c4f44ca7a0aefcf9a966fbfa8aca86c08f6",
    "/i18n/es.json": "e6cf79185c1be407119163c383c2674016ab2ca5",
    "/index.html": "2c1f96640a0dbcd9cb305209b8b32955a707adee",
    "/main.b33a86962736ad465219.js": "f81e0cc80e85a43f3182ffe7008c85a876e4235b",
    "/polyfills.25cec9eb998dda884ce9.js": "f6071cb5c883c5f019ee4e4d9eb41880a96f4c5f",
    "/runtime.7f706c09ba7459279236.js": "078e320cc6fdaf355836c3b1c52b059cdd33fc7e",
    "/styles.6830a36d5d686ed1fb76.js": "b6c4c582957a19835edf56b612884fa6c47543de"
  },
  "navigationUrls": [
    {
      "positive": true,
      "regex": "^\\/.*$"
    },
    {
      "positive": false,
      "regex": "^\\/(?:.+\\/)?[^/]*\\.[^/]*$"
    },
    {
      "positive": false,
      "regex": "^\\/(?:.+\\/)?[^/]*__[^/]*$"
    },
    {
      "positive": false,
      "regex": "^\\/(?:.+\\/)?[^/]*__[^/]*\\/.*$"
    }
  ]
}